[{"id":0,"admission":14,"major":[{"id":0,"name":"ELLT 학과","data":[-1,-1,-1,-1],"classify":"영어대학","theme":"영어대학","notice":"14학번은 영어학부로 신청"},{"id":1,"name":"영미문학문화학과","data":[-1,-1,-1,-1],"classify":"영어대학","theme":"영어대학","notice":"14학번은 영어학부로 신청"},{"id":2,"name":"EICC 학과","data":[-1,-1,-1,-1],"classify":"영어대학","theme":"영어대학","notice":"14학번은 영어학부로 신청"},{"id":3,"name":"프랑스어학부","data":[103,105,108,109],"classify":"서양어대학","theme":"프랑스어학부","notice":"15학번 이전 프랑스어과, 16학번부터 프랑스어학부로 신청"},{"id":4,"name":"독일어과","data":[116,117,120,121],"classify":"서양어대학","theme":null,"notice":null},{"id":5,"name":"노어과","data":[54,56,58,58],"classify":"서양어대학","theme":null,"notice":"자체전형 - 1차 심사: 서류심사-이력서/자기소개서 및 성적증명서&자체전형 - 2차 심사 : 면점심사-1차심사 통과자 중 면접시험 합격자&노어과 홈페이지 : http://hufsrussia.hufs.ac.kr (☎ 02-2173-2284)"},{"id":6,"name":"스페인어과","data":[80,89,92,95],"classify":"서양어대학","theme":"스페인어과","notice":null},{"id":7,"name":"이탈리아어과","data":[42,42,42,42],"classify":"서양어대학","theme":null,"notice":null},{"id":8,"name":"포르투갈어과","data":[39,39,40,40],"classify":"서양어대학","theme":null,"notice":null},{"id":9,"name":"네덜란드어과","data":[45,45,45,45],"classify":"서양어대학","theme":null,"notice":"글로벌캠퍼스 신청 가능 학과"},{"id":10,"name":"스칸디나비아어과","data":[34,35,36,37],"classify":"서양어대학","theme":null,"notice":"글로벌캠퍼스 신청 가능 학과"},{"id":11,"name":"말레이.인도네시아어과","data":[25,28,29,31],"classify":"아시아언어문화대학","theme":"마인어과","notice":null},{"id":12,"name":"아랍어과","data":[53,54,56,58],"classify":"아시아언어문화대학","theme":null,"notice":null},{"id":13,"name":"태국어과","data":[45,45,45,45],"classify":"아시아언어문화대학","theme":null,"notice":null},{"id":14,"name":"베트남어과","data":[30,28,32,32],"classify":"아시아언어문화대학","theme":"베트남어과","notice":"글로벌캠퍼스 신청 가능 학과&기본지원자격 - 평점평균 3.5이상 및 토익 800점 이상&자체전형 - 평점평균 및 토익점수를 종합하여 고득점 선발&영어성적 제출관련 학과사무실 문의 (☎ 02-2173-2300)"},{"id":15,"name":"인도어과","data":[45,45,45,45],"classify":"아시아언어문화대학","theme":null,"notice":null},{"id":16,"name":"터키.아제르바이젠어과","data":[43,44,44,45],"classify":"아시아언어문화대학","theme":null,"notice":"글로벌캠퍼스 신청 가능 학과"},{"id":17,"name":"이란어과","data":[43,43,43,43],"classify":"아시아언어문화대학","theme":null,"notice":"글로벌캠퍼스 신청 가능 학과"},{"id":18,"name":"몽골어과","data":[30,30,30,30],"classify":"아시아언어문화대학","theme":null,"notice":"글로벌캠퍼스 신청 가능 학과"},{"id":19,"name":"중국언어문화전공","data":[54,57,60,61],"classify":"중국어대학","theme":"중국어대","notice":null},{"id":20,"name":"중국외교통상전공","data":[29,39,43,45],"classify":"중국어대학","theme":"중국어대","notice":null},{"id":21,"name":"일본언어문화전공","data":[63,62,61,62],"classify":"일본어대학","theme":"일본어대","notice":"융합일본지역전공학생 신청불가"},{"id":22,"name":"융합일본지역전공","data":[44,45,45,46],"classify":"일본어대학","theme":"일본어대","notice":"일본언어문화전공학생 신청불가"},{"id":23,"name":"정치외교학과","data":[4,13,16,17],"classify":"사회과학대학","theme":"사과대","notice":"글로벌 캠퍼스 학생 신청 가능 학과&자체전형 - 학과교수면접(30%) + 평점평균(70%)&면접 관련 학과 사무실 문의 (☎ 02-2173-2312)"},{"id":24,"name":"행정학과","data":[7,14,17,20],"classify":"사회과학대학","theme":"사과대","notice":"글로벌 캠퍼스 학생 신청 가능 학과&기본지원자격 - 평점평균 3.0이상"},{"id":25,"name":"언론.정보전공","data":[3,4,4,5],"classify":"사회과학대학","theme":"미디어커뮤니케이션학부","notice":"글로벌 캠퍼스 학생 신청 가능 학과"},{"id":26,"name":"광고.PR.브랜딩전공","data":[3,1,0,1],"classify":"사회과학대학","theme":"미디어커뮤니케이션학부","notice":"글로벌 캠퍼스 학생 신청 가능 학과"},{"id":27,"name":"방송.영상.뉴미디어 전공","data":[2,0,2,3],"classify":"사회과학대학","theme":"미디어커뮤니케이션학부","notice":"글로벌 캠퍼스 학생 신청 가능 학과"},{"id":28,"name":"국제통상학과","data":[4,2,3,3],"classify":"상경대학","theme":"상경대학","notice":"글로벌 캠퍼스 학생 신청 가능 학과&2020-1학기에 한해 이중전공신청의 경우 평점평균100%기준 적용&학과 사무실 문의 (☎ 02-2173-2332) 국제통상학과 홈페이지 : http://iel.hufs.ac.kr"},{"id":29,"name":"경제학전공","data":[4,4,5,0],"classify":"상경대학","theme":"상경대학","notice":"글로벌캠퍼스 경제학과 학생 제외 글캠 학생 신청 가능 학과"},{"id":30,"name":"경영학전공","data":[0,4,0,2],"classify":"경영대학","theme":"경영학전공","notice":"글로벌캠퍼스 경영정보학과, 국제경영학과, 국제금융학부(전공/과), GBT학부 학생 제외 글캠 학생 신청 가능 학과&기본지원자격 - 평점평균 3.5이상 + 토익 750/FLEX 654(ibt-flex포함)/TOEFL IBT 87점 이상&자체전형 - 1차심사 : 경영학 기초 필기고사(PASS/FAIL)&2차심사 : 1차심사 PASS 학생 중 평점평균이 높은 순위&시험미응시 또는 Fail 시 미배정(Fail 기준은 경영학부에서 정함)&시험  및 영어성적 제출 관련 해당학과 문의 (☎ 02-2173-2334)경영대학 홈페이지 : http://biz.hufs.ac.kr"},{"id":31,"name":"영어교육과","data":[27,28,28,30],"classify":"사범대학","theme":null,"notice":"사범대 소속 학생만 신청 가능"},{"id":32,"name":"프랑스어교육과","data":[25,25,25,25],"classify":"사범대학","theme":null,"notice":"사범대 소속 학생만 신청 가능"},{"id":33,"name":"독일어교육과","data":[25,25,25,25],"classify":"사범대학","theme":null,"notice":"사범대 소속 학생만 신청 가능"},{"id":34,"name":"한국어교육과","data":[22,23,23,23],"classify":"사범대학","theme":null,"notice":"사범대 소속 학생만 신청 가능"},{"id":35,"name":"중국어교육과","data":[-1,-1,-1,-1],"classify":"사범대학","theme":null,"notice":"사범대 소속 학생만 신청 가능, 16학번부터 지원 가능"},{"id":36,"name":"국제학전공","data":[5,6,7,9],"classify":"국제학부","theme":"국제학부","notice":"글로벌 캠퍼스 학생 신청 가능 학과"},{"id":37,"name":"Language & Deplomacy 전공","data":[-1,-1,-1,-1],"classify":"LD학부","theme":"LD/LT","notice":"17학번부터 신청 가능&기본지원자격 - 성적 : 학점 평균이 4.0이상인 자, 영어 : (택일)TOEIC 885점, TOEFL 103점, FLEX 870점, TEPS 750점 이상 취득 (성적과 영어기준을 동시에 충족해야 함) &자체전형 - 1차심사 : 위의 지원자격 및 자기소개서, 2차심사 : 1차심사 통과자 중 면접을 통하여 결정&부전공 운영하지 않음&문의 : LD학부 사무실(☎ 02-2173-2478)"},{"id":38,"name":"Language & Trade 전공","data":[-1,-1,-1,-1],"classify":"LT학부","theme":"LD/LT","notice":"17학번부터 신청 가능&기본지원자격 - 성적: 학점 평균이 4.0 이상인 자, 영어(택일): TOEIC 885점, TOEFL 103점, FLEX 870점, TEPS 750점 이상 취득 (성적과 영어기준을 동시에 충족해야 함) &기타: 어학실력이 출중함을 입증할 수 있는 경우에는 학점 평균이 3.8 이상일 때 지원이 가능(예: TOEIC 920점, TOEFL 108점, FLEX 900점, TEPS 800점 이상 취득 중 하나)&자체전형 - 1차심사 : 위의 지원자격 및 자기소개서, 2차심사 : 1차심사 통과자 중 면접을 통하여 결정&부전공 운영하지 않음&배정기준 문의 : LT학부 사무실(☎ 02-2173-3350)"},{"id":39,"name":"국가리더전공","data":[43,49,49,51],"classify":"융합전공","theme":"인기융합전공","notice":"07~14학번 합산 선발&글캠 학생은 글캠 여석을 확인하세요.&신청시 캠퍼스는 글로벌로 표시되나 서울캠퍼스 학생은 서울에서 수강"},{"id":40,"name":"융복합소프트웨어전공","data":[3,0,8,5],"classify":"융합전공","theme":"인기융합전공","notice":"07~14학번 합산 선발&글캠 학생은 글캠 여석을 확인하세요.&2014학번 이전 : 교과이수내역(전공주임교수 평가) 및 성적, 2015학번 이후 : 평점평균 100%"},{"id":41,"name":"언어와공학전공","data":[6,8,11,20],"classify":"융합전공","theme":"인기융합전공","notice":"07~14학번 합산 선발&글로벌 캠퍼스 학생 신청 가능 학과"},{"id":42,"name":"디지털인문한국학전공","data":[34,35,39,36],"classify":"융합전공","theme":null,"notice":"07~16학번 합산 선발&글로벌 캠퍼스 학생 신청 가능 학과"},{"id":43,"name":"셰게문화예술경영전공","data":[-2,-2,-2,-2],"classify":"융합전공","theme":null,"notice":"07~16학번 합산 선발&글캠 학생은 글캠 여석을 확인하세요."},{"id":44,"name":"지역경제개발협력전공","data":[0,0,2,2],"classify":"융합전공","theme":null,"notice":"07~16학번 합산 선발&글캠 학생은 글캠 여석을 확인하세요."},{"id":45,"name":"보험계리학전공","data":[5,7,2,7],"classify":"융합전공","theme":null,"notice":"07~16학번 합산 선발&글캠 학생은 글캠 여석을 확인하세요."},{"id":46,"name":"영어학부","data":[164,170,175,181],"classify":"영어대학","theme":"영어대","notice":"14학번은 영어대 이중전공을 영어학부로 신청"},{"id":47,"name":"AI 융합전공","data":[-1,-1,-1,22],"classify":"융합전공","theme":null,"notice":"글로벌 캠퍼스 학생 신청 가능 학과&07~19학번 합산 선발"}]},{"id":1,"admission":15,"major":[{"id":0,"name":"ELLT 학과","data":[58,62,63,65],"classify":"영어대학","theme":"영어대학","notice":null},{"id":1,"name":"영미문학문화학과","data":[83,83,83,82],"classify":"영어대학","theme":"영어대학","notice":null},{"id":2,"name":"EICC 학과","data":[25,27,29,28],"classify":"영어대학","theme":"영어대학","notice":null},{"id":3,"name":"프랑스어학부","data":[92,94,100,108],"classify":"서양어대학","theme":"프랑스어학부","notice":"15학번 이전 프랑스어과, 16학번부터 프랑스어학부로 신청"},{"id":4,"name":"독일어과","data":[103,108,112,112],"classify":"서양어대학","theme":null,"notice":null},{"id":5,"name":"노어과","data":[59,60,61,60],"classify":"서양어대학","theme":null,"notice":"자체전형 - 1차 심사: 서류심사-이력서/자기소개서 및 성적증명서&자체전형 - 2차 심사 : 면점심사-1차심사 통과자 중 면접시험 합격자&노어과 홈페이지 : http://hufsrussia.hufs.ac.kr (☎ 02-2173-2284)"},{"id":6,"name":"스페인어과","data":[46,66,79,85],"classify":"서양어대학","theme":"스페인어과","notice":null},{"id":7,"name":"이탈리아어과","data":[42,43,43,43],"classify":"서양어대학","theme":null,"notice":null},{"id":8,"name":"포르투갈어과","data":[40,39,39,40],"classify":"서양어대학","theme":null,"notice":null},{"id":9,"name":"네덜란드어과","data":[38,39,41,43],"classify":"서양어대학","theme":null,"notice":"글로벌캠퍼스 신청 가능 학과"},{"id":10,"name":"스칸디나비아어과","data":[29,30,31,33],"classify":"서양어대학","theme":null,"notice":"글로벌캠퍼스 신청 가능 학과"},{"id":11,"name":"말레이.인도네시아어과","data":[11,22,26,29],"classify":"아시아언어문화대학","theme":"마인어과","notice":null},{"id":12,"name":"아랍어과","data":[50,53,55,60],"classify":"아시아언어문화대학","theme":null,"notice":null},{"id":13,"name":"태국어과","data":[44,44,44,44],"classify":"아시아언어문화대학","theme":null,"notice":null},{"id":14,"name":"베트남어과","data":[36,34,35,34],"classify":"아시아언어문화대학","theme":"베트남어과","notice":"글로벌캠퍼스 신청 가능 학과&기본지원자격 - 평점평균 3.5이상 및 토익 800점 이상&자체전형 - 평점평균 및 토익점수를 종합하여 고득점 선발&영어성적 제출관련 학과사무실 문의 (☎ 02-2173-2300)"},{"id":15,"name":"인도어과","data":[45,45,45,45],"classify":"아시아언어문화대학","theme":null,"notice":null},{"id":16,"name":"터키.아제르바이젠어과","data":[34,35,36,37],"classify":"아시아언어문화대학","theme":null,"notice":"글로벌캠퍼스 신청 가능 학과"},{"id":17,"name":"이란어과","data":[35,35,38,41],"classify":"아시아언어문화대학","theme":null,"notice":"글로벌캠퍼스 신청 가능 학과"},{"id":18,"name":"몽골어과","data":[27,27,28,28],"classify":"아시아언어문화대학","theme":null,"notice":"글로벌캠퍼스 신청 가능 학과"},{"id":19,"name":"중국언어문화전공","data":[32,42,48,49],"classify":"중국어대학","theme":"중국어대","notice":null},{"id":20,"name":"중국외교통상전공","data":[21,27,34,39],"classify":"중국어대학","theme":"중국어대","notice":null},{"id":21,"name":"일본언어문화전공","data":[39,43,45,49],"classify":"일본어대학","theme":"일본어대","notice":"융합일본지역전공학생 신청불가"},{"id":22,"name":"융합일본지역전공","data":[28,27,30,31],"classify":"일본어대학","theme":"일본어대","notice":"일본언어문화전공학생 신청불가"},{"id":23,"name":"정치외교학과","data":[7,12,12,15],"classify":"사회과학대학","theme":"사과대","notice":"글로벌 캠퍼스 학생 신청 가능 학과&자체전형 - 학과교수면접(30%) + 평점평균(70%)&면접 관련 학과 사무실 문의 (☎ 02-2173-2312)"},{"id":24,"name":"행정학과","data":[15,13,14,15],"classify":"사회과학대학","theme":"사과대","notice":"글로벌 캠퍼스 학생 신청 가능 학과&기본지원자격 - 평점평균 3.0이상"},{"id":25,"name":"언론.정보전공","data":[1,2,3,3],"classify":"사회과학대학","theme":"미디어커뮤니케이션학부","notice":"글로벌 캠퍼스 학생 신청 가능 학과"},{"id":26,"name":"광고.PR.브랜딩전공","data":[0,3,3,1],"classify":"사회과학대학","theme":"미디어커뮤니케이션학부","notice":"글로벌 캠퍼스 학생 신청 가능 학과"},{"id":27,"name":"방송.영상.뉴미디어 전공","data":[1,1,2,0],"classify":"사회과학대학","theme":"미디어커뮤니케이션학부","notice":"글로벌 캠퍼스 학생 신청 가능 학과"},{"id":28,"name":"국제통상학과","data":[1,7,6,3],"classify":"상경대학","theme":"상경대학","notice":"글로벌 캠퍼스 학생 신청 가능 학과&2020-1학기에 한해 이중전공신청의 경우 평점평균100%기준 적용&학과 사무실 문의 (☎ 02-2173-2332) 국제통상학과 홈페이지 : http://iel.hufs.ac.kr"},{"id":29,"name":"경제학전공","data":[8,7,1,0],"classify":"상경대학","theme":"상경대학","notice":"글로벌캠퍼스 경제학과 학생 제외 글캠 학생 신청 가능 학과"},{"id":30,"name":"경영학전공","data":[5,7,0,2],"classify":"경영대학","theme":"경영학전공","notice":"글로벌캠퍼스 경영정보학과, 국제경영학과, 국제금융학부(전공/과), GBT학부 학생 제외 글캠 학생 신청 가능 학과&기본지원자격 - 평점평균 3.5이상 + 토익 750/FLEX 654(ibt-flex포함)/TOEFL IBT 87점 이상&자체전형 - 1차심사 : 경영학 기초 필기고사(PASS/FAIL)&2차심사 : 1차심사 PASS 학생 중 평점평균이 높은 순위&시험미응시 또는 Fail 시 미배정(Fail 기준은 경영학부에서 정함)&시험  및 영어성적 제출 관련 해당학과 문의 (☎ 02-2173-2334)경영대학 홈페이지 : http://biz.hufs.ac.kr"},{"id":31,"name":"영어교육과","data":[26,27,28,29],"classify":"사범대학","theme":null,"notice":"사범대 소속 학생만 신청 가능"},{"id":32,"name":"프랑스어교육과","data":[25,25,25,25],"classify":"사범대학","theme":null,"notice":"사범대 소속 학생만 신청 가능"},{"id":33,"name":"독일어교육과","data":[25,25,25,25],"classify":"사범대학","theme":null,"notice":"사범대 소속 학생만 신청 가능"},{"id":34,"name":"한국어교육과","data":[20,20,20,21],"classify":"사범대학","theme":null,"notice":"사범대 소속 학생만 신청 가능"},{"id":35,"name":"중국어교육과","data":[-1,-1,-1,-1],"classify":"사범대학","theme":null,"notice":"사범대 소속 학생만 신청 가능, 16학번부터 지원 가능"},{"id":36,"name":"국제학전공","data":[3,1,3,5],"classify":"국제학부","theme":"국제학부","notice":"글로벌 캠퍼스 학생 신청 가능 학과"},{"id":37,"name":"Language & Deplomacy 전공","data":[-1,-1,-1,-1],"classify":"LD학부","theme":"LD/LT","notice":"17학번부터 신청 가능&기본지원자격 - 성적 : 학점 평균이 4.0이상인 자, 영어 : (택일)TOEIC 885점, TOEFL 103점, FLEX 870점, TEPS 750점 이상 취득 (성적과 영어기준을 동시에 충족해야 함) &자체전형 - 1차심사 : 위의 지원자격 및 자기소개서, 2차심사 : 1차심사 통과자 중 면접을 통하여 결정&부전공 운영하지 않음&문의 : LD학부 사무실(☎ 02-2173-2478)"},{"id":38,"name":"Language & Trade 전공","data":[-1,-1,-1,-1],"classify":"LT학부","theme":"LD/LT","notice":"17학번부터 신청 가능&기본지원자격 - 성적: 학점 평균이 4.0 이상인 자, 영어(택일): TOEIC 885점, TOEFL 103점, FLEX 870점, TEPS 750점 이상 취득 (성적과 영어기준을 동시에 충족해야 함) &기타: 어학실력이 출중함을 입증할 수 있는 경우에는 학점 평균이 3.8 이상일 때 지원이 가능(예: TOEIC 920점, TOEFL 108점, FLEX 900점, TEPS 800점 이상 취득 중 하나)&자체전형 - 1차심사 : 위의 지원자격 및 자기소개서, 2차심사 : 1차심사 통과자 중 면접을 통하여 결정&부전공 운영하지 않음&배정기준 문의 : LT학부 사무실(☎ 02-2173-3350)"},{"id":39,"name":"국가리더전공","data":[29,27,28,31],"classify":"융합전공","theme":"인기융합전공","notice":"글캠 학생은 글캠 여석을 확인하세요.&신청시 캠퍼스는 글로벌로 표시되나 서울캠퍼스 학생은 서울에서 수강"},{"id":40,"name":"융복합소프트웨어전공","data":[10,15,37,13],"classify":"융합전공","theme":"인기융합전공","notice":"글캠 학생은 글캠 여석을 확인하세요.&2014학번 이전 : 교과이수내역(전공주임교수 평가) 및 성적, 2015학번 이후 : 평점평균 100%"},{"id":41,"name":"언어와공학전공","data":[6,8,11,20],"classify":"융합전공","theme":"인기융합전공","notice":"글로벌 캠퍼스 학생 신청 가능 학과"},{"id":42,"name":"디지털인문한국학전공","data":[34,35,39,36],"classify":"융합전공","theme":null,"notice":"07~16학번 합산 선발&글로벌 캠퍼스 학생 신청 가능 학과"},{"id":43,"name":"셰게문화예술경영전공","data":[-2,-2,-2,-2],"classify":"융합전공","theme":null,"notice":"07~16학번 합산 선발&글캠 학생은 글캠 여석을 확인하세요."},{"id":44,"name":"지역경제개발협력전공","data":[0,0,2,2],"classify":"융합전공","theme":null,"notice":"07~16학번 합산 선발&글캠 학생은 글캠 여석을 확인하세요."},{"id":45,"name":"보험계리학전공","data":[5,7,2,7],"classify":"융합전공","theme":null,"notice":"07~16학번 합산 선발&글캠 학생은 글캠 여석을 확인하세요."},{"id":46,"name":"AI 융합전공","data":[-1,-1,-1,22],"classify":"융합전공","theme":null,"notice":"글로벌 캠퍼스 학생 신청 가능 학과&07~19학번 합산 선발"}]},{"id":2,"admission":16,"major":[{"id":0,"name":"ELLT 학과","data":[80,80,82,82],"classify":"영어대학","theme":"영어대학","notice":null},{"id":1,"name":"영미문학문화학과","data":[84,87,88,87],"classify":"영어대학","theme":"영어대학","notice":null},{"id":2,"name":"EICC 학과","data":[18,20,21,24],"classify":"영어대학","theme":"영어대학","notice":null},{"id":3,"name":"프랑스어학부","data":[69,99,98,102],"classify":"서양어대학","theme":"프랑스어학부","notice":"15학번 이전 프랑스어과, 16학번부터 프랑스어학부로 신청"},{"id":4,"name":"독일어과","data":[105,108,110,112],"classify":"서양어대학","theme":null,"notice":null},{"id":5,"name":"노어과","data":[52,53,53,55],"classify":"서양어대학","theme":null,"notice":"자체전형 - 1차 심사: 서류심사-이력서/자기소개서 및 성적증명서&자체전형 - 2차 심사 : 면점심사-1차심사 통과자 중 면접시험 합격자&노어과 홈페이지 : http://hufsrussia.hufs.ac.kr (☎ 02-2173-2284)"},{"id":6,"name":"스페인어과","data":[15,22,36,45],"classify":"서양어대학","theme":"스페인어과","notice":null},{"id":7,"name":"이탈리아어과","data":[40,40,40,40],"classify":"서양어대학","theme":null,"notice":null},{"id":8,"name":"포르투갈어과","data":[39,40,43,44],"classify":"서양어대학","theme":null,"notice":null},{"id":9,"name":"네덜란드어과","data":[34,38,40,39],"classify":"서양어대학","theme":null,"notice":"글로벌캠퍼스 신청 가능 학과"},{"id":10,"name":"스칸디나비아어과","data":[19,20,29,34],"classify":"서양어대학","theme":null,"notice":"글로벌캠퍼스 신청 가능 학과"},{"id":11,"name":"말레이.인도네시아어과","data":[7,11,11,13],"classify":"아시아언어문화대학","theme":"마인어과","notice":null},{"id":12,"name":"아랍어과","data":[42,43,47,54],"classify":"아시아언어문화대학","theme":null,"notice":null},{"id":13,"name":"태국어과","data":[36,36,40,41],"classify":"아시아언어문화대학","theme":null,"notice":null},{"id":14,"name":"베트남어과","data":[21,23,21,27],"classify":"아시아언어문화대학","theme":"베트남어과","notice":"글로벌캠퍼스 신청 가능 학과&기본지원자격 - 평점평균 3.5이상 및 토익 800점 이상&자체전형 - 평점평균 및 토익점수를 종합하여 고득점 선발&영어성적 제출관련 학과사무실 문의 (☎ 02-2173-2300)"},{"id":15,"name":"인도어과","data":[42,43,43,43],"classify":"아시아언어문화대학","theme":null,"notice":null},{"id":16,"name":"터키.아제르바이젠어과","data":[38,38,39,42],"classify":"아시아언어문화대학","theme":null,"notice":"글로벌캠퍼스 신청 가능 학과"},{"id":17,"name":"이란어과","data":[33,35,38,41],"classify":"아시아언어문화대학","theme":null,"notice":"글로벌캠퍼스 신청 가능 학과"},{"id":18,"name":"몽골어과","data":[30,29,29,29],"classify":"아시아언어문화대학","theme":null,"notice":"글로벌캠퍼스 신청 가능 학과"},{"id":19,"name":"중국언어문화전공","data":[44,45,47,49],"classify":"중국어대학","theme":"중국어대","notice":null},{"id":20,"name":"중국외교통상전공","data":[10,15,20,33],"classify":"중국어대학","theme":"중국어대","notice":null},{"id":21,"name":"일본언어문화전공","data":[31,37,45,52],"classify":"일본어대학","theme":"일본어대","notice":"융합일본지역전공학생 신청불가"},{"id":22,"name":"융합일본지역전공","data":[12,14,15,21],"classify":"일본어대학","theme":"일본어대","notice":"일본언어문화전공학생 신청불가"},{"id":23,"name":"정치외교학과","data":[0,1,2,4],"classify":"사회과학대학","theme":"사과대","notice":"글로벌 캠퍼스 학생 신청 가능 학과&자체전형 - 학과교수면접(30%) + 평점평균(70%)&면접 관련 학과 사무실 문의 (☎ 02-2173-2312)"},{"id":24,"name":"행정학과","data":[9,11,5,11],"classify":"사회과학대학","theme":"사과대","notice":"글로벌 캠퍼스 학생 신청 가능 학과&기본지원자격 - 평점평균 3.0이상"},{"id":25,"name":"언론.정보전공","data":[1,3,2,6],"classify":"사회과학대학","theme":"미디어커뮤니케이션학부","notice":"글로벌 캠퍼스 학생 신청 가능 학과"},{"id":26,"name":"광고.PR.브랜딩전공","data":[0,1,2,2],"classify":"사회과학대학","theme":"미디어커뮤니케이션학부","notice":"글로벌 캠퍼스 학생 신청 가능 학과"},{"id":27,"name":"방송.영상.뉴미디어 전공","data":[0,1,1,1],"classify":"사회과학대학","theme":"미디어커뮤니케이션학부","notice":"글로벌 캠퍼스 학생 신청 가능 학과"},{"id":28,"name":"국제통상학과","data":[1,3,1,2],"classify":"상경대학","theme":"상경대학","notice":"글로벌 캠퍼스 학생 신청 가능 학과&2020-1학기에 한해 이중전공신청의 경우 평점평균100%기준 적용&학과 사무실 문의 (☎ 02-2173-2332) 국제통상학과 홈페이지 : http://iel.hufs.ac.kr"},{"id":29,"name":"경제학전공","data":[5,1,5,7],"classify":"상경대학","theme":"상경대학","notice":"글로벌캠퍼스 경제학과 학생 제외 글캠 학생 신청 가능 학과"},{"id":30,"name":"경영학전공","data":[43,26,4,3],"classify":"경영대학","theme":"경영학전공","notice":"글로벌캠퍼스 경영정보학과, 국제경영학과, 국제금융학부(전공/과), GBT학부 학생 제외 글캠 학생 신청 가능 학과&기본지원자격 - 평점평균 3.5이상 + 토익 750/FLEX 654(ibt-flex포함)/TOEFL IBT 87점 이상&자체전형 - 1차심사 : 경영학 기초 필기고사(PASS/FAIL)&2차심사 : 1차심사 PASS 학생 중 평점평균이 높은 순위&시험미응시 또는 Fail 시 미배정(Fail 기준은 경영학부에서 정함)&시험  및 영어성적 제출 관련 해당학과 문의 (☎ 02-2173-2334)경영대학 홈페이지 : http://biz.hufs.ac.kr"},{"id":31,"name":"영어교육과","data":[25,27,28,27],"classify":"사범대학","theme":null,"notice":"사범대 소속 학생만 신청 가능"},{"id":32,"name":"프랑스어교육과","data":[18,18,18,18],"classify":"사범대학","theme":null,"notice":"사범대 소속 학생만 신청 가능"},{"id":33,"name":"독일어교육과","data":[18,18,18,18],"classify":"사범대학","theme":null,"notice":"사범대 소속 학생만 신청 가능"},{"id":34,"name":"한국어교육과","data":[8,7,6,8],"classify":"사범대학","theme":null,"notice":"사범대 소속 학생만 신청 가능"},{"id":35,"name":"중국어교육과","data":[15,16,16,17],"classify":"사범대학","theme":null,"notice":"사범대 소속 학생만 신청 가능, 16학번부터 지원 가능"},{"id":36,"name":"국제학전공","data":[5,8,7,7],"classify":"국제학부","theme":"국제학부","notice":"글로벌 캠퍼스 학생 신청 가능 학과"},{"id":37,"name":"Language & Deplomacy 전공","data":[-1,-1,-1,-1],"classify":"LD학부","theme":"LD/LT","notice":"글로벌 캠퍼스 학생 신청 가능 학과&17학번부터 신청 가능&기본지원자격 - 성적 : 학점 평균이 4.0이상인 자, 영어 : (택일)TOEIC 885점, TOEFL 103점, FLEX 870점, TEPS 750점 이상 취득 (성적과 영어기준을 동시에 충족해야 함) &자체전형 - 1차심사 : 위의 지원자격 및 자기소개서, 2차심사 : 1차심사 통과자 중 면접을 통하여 결정&부전공 운영하지 않음&문의 : LD학부 사무실(☎ 02-2173-2478)"},{"id":38,"name":"Language & Trade 전공","data":[-1,-1,-1,-1],"classify":"LT학부","theme":"LD/LT","notice":"글로벌 캠퍼스 학생 신청 가능 학과&17학번부터 신청 가능&기본지원자격 - 성적: 학점 평균이 4.0 이상인 자, 영어(택일): TOEIC 885점, TOEFL 103점, FLEX 870점, TEPS 750점 이상 취득 (성적과 영어기준을 동시에 충족해야 함) &기타: 어학실력이 출중함을 입증할 수 있는 경우에는 학점 평균이 3.8 이상일 때 지원이 가능(예: TOEIC 920점, TOEFL 108점, FLEX 900점, TEPS 800점 이상 취득 중 하나)&자체전형 - 1차심사 : 위의 지원자격 및 자기소개서, 2차심사 : 1차심사 통과자 중 면접을 통하여 결정&부전공 운영하지 않음&배정기준 문의 : LT학부 사무실(☎ 02-2173-3350)"},{"id":39,"name":"국가리더전공","data":[25,23,25,29],"classify":"융합전공","theme":"인기융합전공","notice":"글캠 학생은 글캠 여석을 확인하세요.&신청시 캠퍼스는 글로벌로 표시되나 서울캠퍼스 학생은 서울에서 수강"},{"id":40,"name":"융복합소프트웨어전공","data":[5,9,38,5],"classify":"융합전공","theme":"인기융합전공","notice":"글캠 학생은 글캠 여석을 확인하세요.&2014학번 이전 : 교과이수내역(전공주임교수 평가) 및 성적, 2015학번 이후 : 평점평균 100%"},{"id":41,"name":"언어와공학전공","data":[6,8,11,20],"classify":"융합전공","theme":"인기융합전공","notice":"글로벌 캠퍼스 학생 신청 가능 학과"},{"id":42,"name":"디지털인문한국학전공","data":[34,35,39,36],"classify":"융합전공","theme":null,"notice":"07~16학번 합산 선발&글로벌 캠퍼스 학생 신청 가능 학과"},{"id":43,"name":"셰게문화예술경영전공","data":[-2,-2,-2,-2],"classify":"융합전공","theme":null,"notice":"07~16학번 합산 선발&글캠 학생은 글캠 여석을 확인하세요."},{"id":44,"name":"지역경제개발협력전공","data":[0,0,2,2],"classify":"융합전공","theme":null,"notice":"07~16학번 합산 선발&글캠 학생은 글캠 여석을 확인하세요."},{"id":45,"name":"보험계리학전공","data":[5,7,2,7],"classify":"융합전공","theme":null,"notice":"07~16학번 합산 선발&글캠 학생은 글캠 여석을 확인하세요."},{"id":46,"name":"AI 융합전공","data":[-1,-1,-1,22],"classify":"융합전공","theme":null,"notice":"글로벌 캠퍼스 학생 신청 가능 학과&07~19학번 합산 선발"}]},{"id":3,"admission":17,"major":[{"id":0,"name":"ELLT 학과","data":[55,58,61,69],"classify":"영어대학","theme":"영어대학","notice":null},{"id":1,"name":"영미문학문화학과","data":[91,85,85,86],"classify":"영어대학","theme":"영어대학","notice":null},{"id":2,"name":"EICC 학과","data":[15,16,13,27],"classify":"영어대학","theme":"영어대학","notice":null},{"id":3,"name":"프랑스어학부","data":[61,98,99,102],"classify":"서양어대학","theme":"프랑스어학부","notice":"15학번 이전 프랑스어과, 16학번부터 프랑스어학부로 신청"},{"id":4,"name":"독일어과","data":[111,110,110,112],"classify":"서양어대학","theme":null,"notice":null},{"id":5,"name":"노어과","data":[55,55,56,56],"classify":"서양어대학","theme":null,"notice":"자체전형 - 1차 심사: 서류심사-이력서/자기소개서 및 성적증명서&자체전형 - 2차 심사 : 면점심사-1차심사 통과자 중 면접시험 합격자&노어과 홈페이지 : http://hufsrussia.hufs.ac.kr (☎ 02-2173-2284)"},{"id":6,"name":"스페인어과","data":[26,37,38,44],"classify":"서양어대학","theme":"스페인어과","notice":null},{"id":7,"name":"이탈리아어과","data":[42,41,42,43],"classify":"서양어대학","theme":null,"notice":null},{"id":8,"name":"포르투갈어과","data":[38,40,42,41],"classify":"서양어대학","theme":null,"notice":null},{"id":9,"name":"네덜란드어과","data":[41,42,21,42],"classify":"서양어대학","theme":null,"notice":"글로벌캠퍼스 신청 가능 학과"},{"id":10,"name":"스칸디나비아어과","data":[18,21,40,26],"classify":"서양어대학","theme":null,"notice":"글로벌캠퍼스 신청 가능 학과"},{"id":11,"name":"말레이.인도네시아어과","data":[2,2,2,6],"classify":"아시아언어문화대학","theme":"마인어과","notice":null},{"id":12,"name":"아랍어과","data":[37,38,39,44],"classify":"아시아언어문화대학","theme":null,"notice":null},{"id":13,"name":"태국어과","data":[38,39,39,40],"classify":"아시아언어문화대학","theme":null,"notice":null},{"id":14,"name":"베트남어과","data":[22,24,26,30],"classify":"아시아언어문화대학","theme":"베트남어과","notice":"글로벌캠퍼스 신청 가능 학과&기본지원자격 - 평점평균 3.5이상 및 토익 800점 이상&자체전형 - 평점평균 및 토익점수를 종합하여 고득점 선발&영어성적 제출관련 학과사무실 문의 (☎ 02-2173-2300)"},{"id":15,"name":"인도어과","data":[45,45,45,45],"classify":"아시아언어문화대학","theme":null,"notice":null},{"id":16,"name":"터키.아제르바이젠어과","data":[41,43,43,43],"classify":"아시아언어문화대학","theme":null,"notice":"글로벌캠퍼스 신청 가능 학과"},{"id":17,"name":"이란어과","data":[39,41,41,42],"classify":"아시아언어문화대학","theme":null,"notice":"글로벌캠퍼스 신청 가능 학과"},{"id":18,"name":"몽골어과","data":[30,30,29,30],"classify":"아시아언어문화대학","theme":null,"notice":"글로벌캠퍼스 신청 가능 학과"},{"id":19,"name":"중국언어문화전공","data":[44,25,23,40],"classify":"중국어대학","theme":"중국어대","notice":null},{"id":20,"name":"중국외교통상전공","data":[0,0,1,14],"classify":"중국어대학","theme":"중국어대","notice":null},{"id":21,"name":"일본언어문화전공","data":[21,26,30,38],"classify":"일본어대학","theme":"일본어대","notice":"융합일본지역전공학생 신청불가"},{"id":22,"name":"융합일본지역전공","data":[1,3,10,17],"classify":"일본어대학","theme":"일본어대","notice":"일본언어문화전공학생 신청불가"},{"id":23,"name":"정치외교학과","data":[5,8,1,2],"classify":"사회과학대학","theme":"사과대","notice":"글로벌 캠퍼스 학생 신청 가능 학과&자체전형 - 학과교수면접(30%) + 평점평균(70%)&면접 관련 학과 사무실 문의 (☎ 02-2173-2312)"},{"id":24,"name":"행정학과","data":[5,5,7,6],"classify":"사회과학대학","theme":"사과대","notice":"글로벌 캠퍼스 학생 신청 가능 학과&기본지원자격 - 평점평균 3.0이상"},{"id":25,"name":"언론.정보전공","data":[1,4,0,4],"classify":"사회과학대학","theme":"미디어커뮤니케이션학부","notice":"글로벌 캠퍼스 학생 신청 가능 학과"},{"id":26,"name":"광고.PR.브랜딩전공","data":[3,1,2,2],"classify":"사회과학대학","theme":"미디어커뮤니케이션학부","notice":"글로벌 캠퍼스 학생 신청 가능 학과"},{"id":27,"name":"방송.영상.뉴미디어 전공","data":[0,1,0,2],"classify":"사회과학대학","theme":"미디어커뮤니케이션학부","notice":"글로벌 캠퍼스 학생 신청 가능 학과"},{"id":28,"name":"국제통상학과","data":[1,1,3,4],"classify":"상경대학","theme":"상경대학","notice":"글로벌 캠퍼스 학생 신청 가능 학과&2020-1학기에 한해 이중전공신청의 경우 평점평균100%기준 적용&학과 사무실 문의 (☎ 02-2173-2332) 국제통상학과 홈페이지 : http://iel.hufs.ac.kr"},{"id":29,"name":"경제학전공","data":[2,1,0,5],"classify":"상경대학","theme":"상경대학","notice":"글로벌캠퍼스 경제학과 학생 제외 글캠 학생 신청 가능 학과"},{"id":30,"name":"경영학전공","data":[122,89,66,57],"classify":"경영대학","theme":"경영학전공","notice":"글로벌캠퍼스 경영정보학과, 국제경영학과, 국제금융학부(전공/과), GBT학부 학생 제외 글캠 학생 신청 가능 학과&기본지원자격 - 평점평균 3.5이상 + 토익 750/FLEX 654(ibt-flex포함)/TOEFL IBT 87점 이상&자체전형 - 1차심사 : 경영학 기초 필기고사(PASS/FAIL)&2차심사 : 1차심사 PASS 학생 중 평점평균이 높은 순위&시험미응시 또는 Fail 시 미배정(Fail 기준은 경영학부에서 정함)&시험  및 영어성적 제출 관련 해당학과 문의 (☎ 02-2173-2334)경영대학 홈페이지 : http://biz.hufs.ac.kr"},{"id":31,"name":"영어교육과","data":[25,25,25,26],"classify":"사범대학","theme":null,"notice":"사범대 소속 학생만 신청 가능"},{"id":32,"name":"프랑스어교육과","data":[18,18,18,18],"classify":"사범대학","theme":null,"notice":"사범대 소속 학생만 신청 가능"},{"id":33,"name":"독일어교육과","data":[18,18,18,18],"classify":"사범대학","theme":null,"notice":"사범대 소속 학생만 신청 가능"},{"id":34,"name":"한국어교육과","data":[15,15,18,17],"classify":"사범대학","theme":null,"notice":"사범대 소속 학생만 신청 가능"},{"id":35,"name":"중국어교육과","data":[17,17,16,15],"classify":"사범대학","theme":null,"notice":"사범대 소속 학생만 신청 가능, 16학번부터 지원 가능"},{"id":36,"name":"국제학전공","data":[0,2,6,7],"classify":"국제학부","theme":"국제학부","notice":"글로벌 캠퍼스 학생 신청 가능 학과"},{"id":37,"name":"Language & Deplomacy 전공","data":[46,46,46,46],"classify":"LD학부","theme":"LD/LT","notice":"글로벌 캠퍼스 학생 신청 가능 학과&17학번부터 신청 가능&기본지원자격 - 성적 : 학점 평균이 4.0이상인 자, 영어 : (택일)TOEIC 885점, TOEFL 103점, FLEX 870점, TEPS 750점 이상 취득 (성적과 영어기준을 동시에 충족해야 함) &자체전형 - 1차심사 : 위의 지원자격 및 자기소개서, 2차심사 : 1차심사 통과자 중 면접을 통하여 결정&부전공 운영하지 않음&문의 : LD학부 사무실(☎ 02-2173-2478)"},{"id":38,"name":"Language & Trade 전공","data":[24,24,23,23],"classify":"LT학부","theme":"LD/LT","notice":"글로벌 캠퍼스 학생 신청 가능 학과&17학번부터 신청 가능&기본지원자격 - 성적: 학점 평균이 4.0 이상인 자, 영어(택일): TOEIC 885점, TOEFL 103점, FLEX 870점, TEPS 750점 이상 취득 (성적과 영어기준을 동시에 충족해야 함) &기타: 어학실력이 출중함을 입증할 수 있는 경우에는 학점 평균이 3.8 이상일 때 지원이 가능(예: TOEIC 920점, TOEFL 108점, FLEX 900점, TEPS 800점 이상 취득 중 하나)&자체전형 - 1차심사 : 위의 지원자격 및 자기소개서, 2차심사 : 1차심사 통과자 중 면접을 통하여 결정&부전공 운영하지 않음&배정기준 문의 : LT학부 사무실(☎ 02-2173-3350)"},{"id":39,"name":"국가리더전공","data":[3,6,4,4],"classify":"융합전공","theme":"인기융합전공","notice":"글캠 학생은 글캠 여석을 확인하세요.&신청시 캠퍼스는 글로벌로 표시되나 서울캠퍼스 학생은 서울에서 수강"},{"id":40,"name":"융복합소프트웨어전공","data":[7,7,21,1],"classify":"융합전공","theme":"인기융합전공","notice":"글캠 학생은 글캠 여석을 확인하세요.&2014학번 이전 : 교과이수내역(전공주임교수 평가) 및 성적, 2015학번 이후 : 평점평균 100%"},{"id":41,"name":"언어와공학전공","data":[29,27,28,32],"classify":"융합전공","theme":"인기융합전공","notice":"글로벌 캠퍼스 학생 신청 가능 학과"},{"id":42,"name":"디지털인문한국학전공","data":[31,35,37,38],"classify":"융합전공","theme":null,"notice":"글로벌 캠퍼스 학생 신청 가능 학과"},{"id":43,"name":"셰게문화예술경영전공","data":[10,12,8,12],"classify":"융합전공","theme":null,"notice":"글캠 학생은 글캠 여석을 확인하세요."},{"id":44,"name":"지역경제개발협력전공","data":[2,1,1,1],"classify":"융합전공","theme":null,"notice":"글캠 학생은 글캠 여석을 확인하세요."},{"id":45,"name":"보험계리학전공","data":[7,8,8,8],"classify":"융합전공","theme":null,"notice":"글캠 학생은 글캠 여석을 확인하세요."},{"id":46,"name":"AI 융합전공","data":[-1,-1,-1,22],"classify":"융합전공","theme":null,"notice":"글로벌 캠퍼스 학생 신청 가능 학과&07~19학번 모두가 여석에 포함됩니다."}]},{"id":4,"admission":18,"major":[{"id":0,"name":"ELLT 학과","data":[-1,55,44,46],"classify":"영어대학","theme":"영어대학","notice":null},{"id":1,"name":"영미문학문화학과","data":[-1,95,94,90],"classify":"영어대학","theme":"영어대학","notice":null},{"id":2,"name":"EICC 학과","data":[-1,25,21,17],"classify":"영어대학","theme":"영어대학","notice":null},{"id":3,"name":"프랑스어학부","data":[-1,80,78,97],"classify":"서양어대학","theme":"프랑스어학부","notice":"15학번 이전 프랑스어과, 16학번부터 프랑스어학부로 신청"},{"id":4,"name":"독일어과","data":[-1,122,121,122],"classify":"서양어대학","theme":null,"notice":null},{"id":5,"name":"노어과","data":[-1,53,54,53],"classify":"서양어대학","theme":null,"notice":"자체전형 - 1차 심사: 서류심사-이력서/자기소개서 및 성적증명서&자체전형 - 2차 심사 : 면점심사-1차심사 통과자 중 면접시험 합격자&노어과 홈페이지 : http://hufsrussia.hufs.ac.kr (☎ 02-2173-2284)"},{"id":6,"name":"스페인어과","data":[-1,36,33,43],"classify":"서양어대학","theme":"스페인어과","notice":null},{"id":7,"name":"이탈리아어과","data":[-1,37,37,37],"classify":"서양어대학","theme":null,"notice":null},{"id":8,"name":"포르투갈어과","data":[-1,43,43,42],"classify":"서양어대학","theme":null,"notice":null},{"id":9,"name":"네덜란드어과","data":[-1,44,35,41],"classify":"서양어대학","theme":null,"notice":"글로벌캠퍼스 신청 가능 학과"},{"id":10,"name":"스칸디나비아어과","data":[-1,36,44,37],"classify":"서양어대학","theme":null,"notice":"글로벌캠퍼스 신청 가능 학과"},{"id":11,"name":"말레이.인도네시아어과","data":[-1,0,3,10],"classify":"아시아언어문화대학","theme":"마인어과","notice":null},{"id":12,"name":"아랍어과","data":[-1,42,45,45],"classify":"아시아언어문화대학","theme":null,"notice":null},{"id":13,"name":"태국어과","data":[-1,40,41,42],"classify":"아시아언어문화대학","theme":null,"notice":null},{"id":14,"name":"베트남어과","data":[-1,24,26,28],"classify":"아시아언어문화대학","theme":"베트남어과","notice":"글로벌캠퍼스 신청 가능 학과&기본지원자격 - 평점평균 3.5이상 및 토익 800점 이상&자체전형 - 평점평균 및 토익점수를 종합하여 고득점 선발&영어성적 제출관련 학과사무실 문의 (☎ 02-2173-2300)"},{"id":15,"name":"인도어과","data":[-1,45,45,45],"classify":"아시아언어문화대학","theme":null,"notice":null},{"id":16,"name":"터키.아제르바이젠어과","data":[-1,42,42,42],"classify":"아시아언어문화대학","theme":null,"notice":"글로벌캠퍼스 신청 가능 학과"},{"id":17,"name":"이란어과","data":[-1,43,43,45],"classify":"아시아언어문화대학","theme":null,"notice":"글로벌캠퍼스 신청 가능 학과"},{"id":18,"name":"몽골어과","data":[-1,28,29,29],"classify":"아시아언어문화대학","theme":null,"notice":"글로벌캠퍼스 신청 가능 학과"},{"id":19,"name":"중국언어문화전공","data":[-1,64,55,60],"classify":"중국어대학","theme":"중국어대","notice":null},{"id":20,"name":"중국외교통상전공","data":[-1,2,0,0],"classify":"중국어대학","theme":"중국어대","notice":null},{"id":21,"name":"일본언어문화전공","data":[-1,61,51,55],"classify":"일본어대학","theme":"일본어대","notice":"융합일본지역전공학생 신청불가"},{"id":22,"name":"융합일본지역전공","data":[-1,14,12,10],"classify":"일본어대학","theme":"일본어대","notice":"일본언어문화전공학생 신청불가"},{"id":23,"name":"정치외교학과","data":[-1,12,1,0],"classify":"사회과학대학","theme":"사과대","notice":"글로벌 캠퍼스 학생 신청 가능 학과&자체전형 - 학과교수면접(30%) + 평점평균(70%)&면접 관련 학과 사무실 문의 (☎ 02-2173-2312)"},{"id":24,"name":"행정학과","data":[-1,3,0,3],"classify":"사회과학대학","theme":"사과대","notice":"글로벌 캠퍼스 학생 신청 가능 학과&기본지원자격 - 평점평균 3.0이상"},{"id":25,"name":"언론.정보전공","data":[-1,1,3,1],"classify":"사회과학대학","theme":"미디어커뮤니케이션학부","notice":"글로벌 캠퍼스 학생 신청 가능 학과"},{"id":26,"name":"광고.PR.브랜딩전공","data":[-1,0,0,5],"classify":"사회과학대학","theme":"미디어커뮤니케이션학부","notice":"글로벌 캠퍼스 학생 신청 가능 학과"},{"id":27,"name":"방송.영상.뉴미디어 전공","data":[-1,0,0,1],"classify":"사회과학대학","theme":"미디어커뮤니케이션학부","notice":"글로벌 캠퍼스 학생 신청 가능 학과"},{"id":28,"name":"국제통상학과","data":[-1,3,0,2],"classify":"상경대학","theme":"상경대학","notice":"글로벌 캠퍼스 학생 신청 가능 학과&2020-1학기에 한해 이중전공신청의 경우 평점평균100%기준 적용&학과 사무실 문의 (☎ 02-2173-2332) 국제통상학과 홈페이지 : http://iel.hufs.ac.kr"},{"id":29,"name":"경제학전공","data":[-1,7,0,8],"classify":"상경대학","theme":"상경대학","notice":"글로벌캠퍼스 경제학과 학생 제외 글캠 학생 신청 가능 학과"},{"id":30,"name":"경영학전공","data":[-1,169,138,110],"classify":"경영대학","theme":"경영학전공","notice":"글로벌캠퍼스 경영정보학과, 국제경영학과, 국제금융학부(전공/과), GBT학부 학생 제외 글캠 학생 신청 가능 학과&기본지원자격 - 평점평균 3.5이상 + 토익 750/FLEX 654(ibt-flex포함)/TOEFL IBT 87점 이상&자체전형 - 1차심사 : 경영학 기초 필기고사(PASS/FAIL)&2차심사 : 1차심사 PASS 학생 중 평점평균이 높은 순위&시험미응시 또는 Fail 시 미배정(Fail 기준은 경영학부에서 정함)&시험  및 영어성적 제출 관련 해당학과 문의 (☎ 02-2173-2334)경영대학 홈페이지 : http://biz.hufs.ac.kr"},{"id":31,"name":"영어교육과","data":[-1,26,26,26],"classify":"사범대학","theme":null,"notice":"사범대 소속 학생만 신청 가능"},{"id":32,"name":"프랑스어교육과","data":[-1,18,18,18],"classify":"사범대학","theme":null,"notice":"사범대 소속 학생만 신청 가능"},{"id":33,"name":"독일어교육과","data":[-1,17,16,17],"classify":"사범대학","theme":null,"notice":"사범대 소속 학생만 신청 가능"},{"id":34,"name":"한국어교육과","data":[-1,10,11,12],"classify":"사범대학","theme":null,"notice":"사범대 소속 학생만 신청 가능"},{"id":35,"name":"중국어교육과","data":[-1,17,17,17],"classify":"사범대학","theme":null,"notice":"사범대 소속 학생만 신청 가능, 16학번부터 지원 가능"},{"id":36,"name":"국제학전공","data":[-1,0,2,5],"classify":"국제학부","theme":"국제학부","notice":"글로벌 캠퍼스 학생 신청 가능 학과"},{"id":37,"name":"Language & Deplomacy 전공","data":[-1,47,45,45],"classify":"LD학부","theme":"LD/LT","notice":"글로벌 캠퍼스 학생 신청 가능 학과&17학번부터 신청 가능&기본지원자격 - 성적 : 학점 평균이 4.0이상인 자, 영어 : (택일)TOEIC 885점, TOEFL 103점, FLEX 870점, TEPS 750점 이상 취득 (성적과 영어기준을 동시에 충족해야 함) &자체전형 - 1차심사 : 위의 지원자격 및 자기소개서, 2차심사 : 1차심사 통과자 중 면접을 통하여 결정&부전공 운영하지 않음&문의 : LD학부 사무실(☎ 02-2173-2478)"},{"id":38,"name":"Language & Trade 전공","data":[-1,26,25,24],"classify":"LT학부","theme":"LD/LT","notice":"글로벌 캠퍼스 학생 신청 가능 학과&17학번부터 신청 가능&기본지원자격 - 성적: 학점 평균이 4.0 이상인 자, 영어(택일): TOEIC 885점, TOEFL 103점, FLEX 870점, TEPS 750점 이상 취득 (성적과 영어기준을 동시에 충족해야 함) &기타: 어학실력이 출중함을 입증할 수 있는 경우에는 학점 평균이 3.8 이상일 때 지원이 가능(예: TOEIC 920점, TOEFL 108점, FLEX 900점, TEPS 800점 이상 취득 중 하나)&자체전형 - 1차심사 : 위의 지원자격 및 자기소개서, 2차심사 : 1차심사 통과자 중 면접을 통하여 결정&부전공 운영하지 않음&배정기준 문의 : LT학부 사무실(☎ 02-2173-3350)"},{"id":39,"name":"국가리더전공","data":[-1,3,4,5],"classify":"융합전공","theme":"인기융합전공","notice":"글캠 학생은 글캠 여석을 확인하세요.&신청시 캠퍼스는 글로벌로 표시되나 서울캠퍼스 학생은 서울에서 수강"},{"id":40,"name":"융복합소프트웨어전공","data":[-1,0,16,4],"classify":"융합전공","theme":"인기융합전공","notice":"글캠 학생은 글캠 여석을 확인하세요.&2014학번 이전 : 교과이수내역(전공주임교수 평가) 및 성적, 2015학번 이후 : 평점평균 100%"},{"id":41,"name":"언어와공학전공","data":[-1,32,32,34],"classify":"융합전공","theme":"인기융합전공","notice":"글로벌 캠퍼스 학생 신청 가능 학과"},{"id":42,"name":"디지털인문한국학전공","data":[-1,46,47,47],"classify":"융합전공","theme":null,"notice":"글로벌 캠퍼스 학생 신청 가능 학과"},{"id":43,"name":"셰게문화예술경영전공","data":[-1,0,5,5],"classify":"융합전공","theme":null,"notice":"글캠 학생은 글캠 여석을 확인하세요."},{"id":44,"name":"지역경제개발협력전공","data":[-1,0,0,1],"classify":"융합전공","theme":null,"notice":"글캠 학생은 글캠 여석을 확인하세요."},{"id":45,"name":"보험계리학전공","data":[-1,4,3,5],"classify":"융합전공","theme":null,"notice":"글캠 학생은 글캠 여석을 확인하세요."},{"id":46,"name":"AI 융합전공","data":[-1,-1,-1,22],"classify":"융합전공","theme":null,"notice":"글로벌 캠퍼스 학생 신청 가능 학과&07~19학번 모두가 여석에 포함됩니다."}]},{"id":5,"admission":19,"major":[{"id":0,"name":"ELLT 학과","data":[-1,-1,-1,71],"classify":"영어대학","theme":"영어대학","notice":null},{"id":1,"name":"영미문학문화학과","data":[-1,-1,-1,91],"classify":"영어대학","theme":"영어대학","notice":null},{"id":2,"name":"EICC 학과","data":[-1,-1,-1,32],"classify":"영어대학","theme":"영어대학","notice":null},{"id":3,"name":"프랑스어학부","data":[-1,-1,-1,82],"classify":"서양어대학","theme":"프랑스어학부","notice":"15학번 이전 프랑스어과, 16학번부터 프랑스어학부로 신청"},{"id":4,"name":"독일어과","data":[-1,-1,-1,110],"classify":"서양어대학","theme":null,"notice":null},{"id":5,"name":"노어과","data":[-1,-1,-1,56],"classify":"서양어대학","theme":null,"notice":"자체전형 - 1차 심사: 서류심사-이력서/자기소개서 및 성적증명서&자체전형 - 2차 심사 : 면점심사-1차심사 통과자 중 면접시험 합격자&노어과 홈페이지 : http://hufsrussia.hufs.ac.kr (☎ 02-2173-2284)"},{"id":6,"name":"스페인어과","data":[-1,-1,-1,42],"classify":"서양어대학","theme":"스페인어과","notice":null},{"id":7,"name":"이탈리아어과","data":[-1,-1,-1,45],"classify":"서양어대학","theme":null,"notice":null},{"id":8,"name":"포르투갈어과","data":[-1,-1,-1,44],"classify":"서양어대학","theme":null,"notice":null},{"id":9,"name":"네덜란드어과","data":[-1,-1,-1,39],"classify":"서양어대학","theme":null,"notice":"글로벌캠퍼스 신청 가능 학과"},{"id":10,"name":"스칸디나비아어과","data":[-1,-1,-1,30],"classify":"서양어대학","theme":null,"notice":"글로벌캠퍼스 신청 가능 학과"},{"id":11,"name":"말레이.인도네시아어과","data":[-1,-1,-1,1],"classify":"아시아언어문화대학","theme":"마인어과","notice":null},{"id":12,"name":"아랍어과","data":[-1,-1,-1,48],"classify":"아시아언어문화대학","theme":null,"notice":null},{"id":13,"name":"태국어과","data":[-1,-1,-1,45],"classify":"아시아언어문화대학","theme":null,"notice":null},{"id":14,"name":"베트남어과","data":[-1,-1,-1,41],"classify":"아시아언어문화대학","theme":"베트남어과","notice":"글로벌캠퍼스 신청 가능 학과&기본지원자격 - 평점평균 3.5이상 및 토익 800점 이상&자체전형 - 평점평균 및 토익점수를 종합하여 고득점 선발&영어성적 제출관련 학과사무실 문의 (☎ 02-2173-2300)"},{"id":15,"name":"인도어과","data":[-1,-1,-1,45],"classify":"아시아언어문화대학","theme":null,"notice":null},{"id":16,"name":"터키.아제르바이젠어과","data":[-1,-1,-1,44],"classify":"아시아언어문화대학","theme":null,"notice":"글로벌캠퍼스 신청 가능 학과"},{"id":17,"name":"이란어과","data":[-1,-1,-1,44],"classify":"아시아언어문화대학","theme":null,"notice":"글로벌캠퍼스 신청 가능 학과"},{"id":18,"name":"몽골어과","data":[-1,-1,-1,29],"classify":"아시아언어문화대학","theme":null,"notice":"글로벌캠퍼스 신청 가능 학과"},{"id":19,"name":"중국언어문화전공","data":[-1,-1,-1,62],"classify":"중국어대학","theme":"중국어대","notice":null},{"id":20,"name":"중국외교통상전공","data":[-1,-1,-1,24],"classify":"중국어대학","theme":"중국어대","notice":null},{"id":21,"name":"일본언어문화전공","data":[-1,-1,-1,59],"classify":"일본어대학","theme":"일본어대","notice":"융합일본지역전공학생 신청불가"},{"id":22,"name":"융합일본지역전공","data":[-1,-1,-1,40],"classify":"일본어대학","theme":"일본어대","notice":"일본언어문화전공학생 신청불가"},{"id":23,"name":"정치외교학과","data":[-1,-1,-1,3],"classify":"사회과학대학","theme":"사과대","notice":"글로벌 캠퍼스 학생 신청 가능 학과&자체전형 - 학과교수면접(30%) + 평점평균(70%)&면접 관련 학과 사무실 문의 (☎ 02-2173-2312)"},{"id":24,"name":"행정학과","data":[-1,-1,-1,2],"classify":"사회과학대학","theme":"사과대","notice":"글로벌 캠퍼스 학생 신청 가능 학과&기본지원자격 - 평점평균 3.0이상"},{"id":25,"name":"언론.정보전공","data":[-1,-1,-1,1],"classify":"사회과학대학","theme":"미디어커뮤니케이션학부","notice":"글로벌 캠퍼스 학생 신청 가능 학과"},{"id":26,"name":"광고.PR.브랜딩전공","data":[-1,-1,-1,1],"classify":"사회과학대학","theme":"미디어커뮤니케이션학부","notice":"글로벌 캠퍼스 학생 신청 가능 학과"},{"id":27,"name":"방송.영상.뉴미디어 전공","data":[-1,-1,-1,0],"classify":"사회과학대학","theme":"미디어커뮤니케이션학부","notice":"글로벌 캠퍼스 학생 신청 가능 학과"},{"id":28,"name":"국제통상학과","data":[-1,-1,-1,3],"classify":"상경대학","theme":"상경대학","notice":"글로벌 캠퍼스 학생 신청 가능 학과&2020-1학기에 한해 이중전공신청의 경우 평점평균100%기준 적용&학과 사무실 문의 (☎ 02-2173-2332) 국제통상학과 홈페이지 : http://iel.hufs.ac.kr"},{"id":29,"name":"경제학전공","data":[-1,-1,-1,0],"classify":"상경대학","theme":"상경대학","notice":"글로벌캠퍼스 경제학과 학생 제외 글캠 학생 신청 가능 학과"},{"id":30,"name":"경영학전공","data":[-1,-1,-1,205],"classify":"경영대학","theme":"경영학전공","notice":"글로벌캠퍼스 경영정보학과, 국제경영학과, 국제금융학부(전공/과), GBT학부 학생 제외 글캠 학생 신청 가능 학과&기본지원자격 - 평점평균 3.5이상 + 토익 750/FLEX 654(ibt-flex포함)/TOEFL IBT 87점 이상&자체전형 - 1차심사 : 경영학 기초 필기고사(PASS/FAIL)&2차심사 : 1차심사 PASS 학생 중 평점평균이 높은 순위&시험미응시 또는 Fail 시 미배정(Fail 기준은 경영학부에서 정함)&시험  및 영어성적 제출 관련 해당학과 문의 (☎ 02-2173-2334)경영대학 홈페이지 : http://biz.hufs.ac.kr"},{"id":31,"name":"영어교육과","data":[-1,-1,-1,30],"classify":"사범대학","theme":null,"notice":"사범대 소속 학생만 신청 가능"},{"id":32,"name":"프랑스어교육과","data":[-1,-1,-1,18],"classify":"사범대학","theme":null,"notice":"사범대 소속 학생만 신청 가능"},{"id":33,"name":"독일어교육과","data":[-1,-1,-1,18],"classify":"사범대학","theme":null,"notice":"사범대 소속 학생만 신청 가능"},{"id":34,"name":"한국어교육과","data":[-1,-1,-1,14],"classify":"사범대학","theme":null,"notice":"사범대 소속 학생만 신청 가능"},{"id":35,"name":"중국어교육과","data":[-1,-1,-1,16],"classify":"사범대학","theme":null,"notice":"사범대 소속 학생만 신청 가능, 16학번부터 지원 가능"},{"id":36,"name":"국제학전공","data":[-1,-1,-1,1],"classify":"국제학부","theme":"국제학부","notice":"글로벌 캠퍼스 학생 신청 가능 학과"},{"id":37,"name":"Language & Deplomacy 전공","data":[-1,-1,-1,49],"classify":"LD학부","theme":"LD/LT","notice":"글로벌 캠퍼스 학생 신청 가능 학과&17학번부터 신청 가능&기본지원자격 - 성적 : 학점 평균이 4.0이상인 자, 영어 : (택일)TOEIC 885점, TOEFL 103점, FLEX 870점, TEPS 750점 이상 취득 (성적과 영어기준을 동시에 충족해야 함) &자체전형 - 1차심사 : 위의 지원자격 및 자기소개서, 2차심사 : 1차심사 통과자 중 면접을 통하여 결정&부전공 운영하지 않음&문의 : LD학부 사무실(☎ 02-2173-2478)"},{"id":38,"name":"Language & Trade 전공","data":[-1,-1,-1,27],"classify":"LT학부","theme":"LD/LT","notice":"글로벌 캠퍼스 학생 신청 가능 학과&17학번부터 신청 가능&기본지원자격 - 성적: 학점 평균이 4.0 이상인 자, 영어(택일): TOEIC 885점, TOEFL 103점, FLEX 870점, TEPS 750점 이상 취득 (성적과 영어기준을 동시에 충족해야 함) &기타: 어학실력이 출중함을 입증할 수 있는 경우에는 학점 평균이 3.8 이상일 때 지원이 가능(예: TOEIC 920점, TOEFL 108점, FLEX 900점, TEPS 800점 이상 취득 중 하나)&자체전형 - 1차심사 : 위의 지원자격 및 자기소개서, 2차심사 : 1차심사 통과자 중 면접을 통하여 결정&부전공 운영하지 않음&배정기준 문의 : LT학부 사무실(☎ 02-2173-3350)"},{"id":39,"name":"국가리더전공","data":[-1,-1,-1,1],"classify":"융합전공","theme":"인기융합전공","notice":"글캠 학생은 글캠 여석을 확인하세요.&신청시 캠퍼스는 글로벌로 표시되나 서울캠퍼스 학생은 서울에서 수강"},{"id":40,"name":"융복합소프트웨어전공","data":[-1,-1,-1,24],"classify":"융합전공","theme":"인기융합전공","notice":"글캠 학생은 글캠 여석을 확인하세요.&2014학번 이전 : 교과이수내역(전공주임교수 평가) 및 성적, 2015학번 이후 : 평점평균 100%"},{"id":41,"name":"언어와공학전공","data":[-1,-1,-1,44],"classify":"융합전공","theme":"인기융합전공","notice":"글로벌 캠퍼스 학생 신청 가능 학과"},{"id":42,"name":"디지털인문한국학전공","data":[-1,-1,-1,48],"classify":"융합전공","theme":null,"notice":"글로벌 캠퍼스 학생 신청 가능 학과"},{"id":43,"name":"셰게문화예술경영전공","data":[-1,-1,-1,16],"classify":"융합전공","theme":null,"notice":"글캠 학생은 글캠 여석을 확인하세요."},{"id":44,"name":"지역경제개발협력전공","data":[-1,-1,-1,0],"classify":"융합전공","theme":null,"notice":"글캠 학생은 글캠 여석을 확인하세요."},{"id":45,"name":"보험계리학전공","data":[-1,-1,-1,7],"classify":"융합전공","theme":null,"notice":"글캠 학생은 글캠 여석을 확인하세요."},{"id":46,"name":"AI 융합전공","data":[-1,-1,-1,22],"classify":"융합전공","theme":null,"notice":"글로벌 캠퍼스 학생 신청 가능 학과&07~19학번 모두가 여석에 포함됩니다."}]}]